{
    "enabled": true,
    "neededInstalledMods": [],
    "neededUninstalledMods": [],
    "spawns": [
        {
            "id": "bognmarrow-1",
            "pokemon": "bognmarrow",
            "type": "pokemon",
            "spawnablePositionType": "grounded",
            "bucket": "uncommon",
            "level": "36-60",
            "weight": 4,
            "weightMultiplier": {
                "multiplier": 1.5,
                "condition": {
                    "timeRange": "night"
                }
            },
            "condition": {
                "canSeeSky": false,
                "biomes": [
                    "#cobblemon:is_swamp",
					"#cobblemon:is_mushroom"
                ]
            },
            "anticondition": {
                "biomes": [
                   "#cobblemon:is_deep_dark",
                   "#cobblemon:is_hills",
                   "#cobblemon:is_snowy_forest",
                   "#cobblemon:is_snowy_taiga",
                   "#cobblemon:is_taiga",
				   "#cobblemon:is_desert"
                ]
            }
        },
        {
            "id": "bognmarrow-mushroom",
            "pokemon": "bognmarrow",
            "type": "pokemon",
            "spawnablePositionType": "grounded",
            "bucket": "uncommon",
            "level": "36-50",
            "weight": 3.0,
            "condition": {
                "neededNearbyBlocks": [
                    "ribbits:toadstool",
                    "ribbits:red_toadstool",
                    "ribbits:brown_toadstool",
                    "ribbits:toadstool_stem",
                    "minecraft:red_mushroom_block",
                    "minecraft:mushroom_stem",
                    "minecraft:brown_mushroom_block",
                    "minecraft:brown_mushroom",
                    "minecraft:red_mushroom"
                ]
            }
        }
   ]
}
